ocpiupdate/__init__.py
ocpiupdate/config.py
ocpiupdate/ocpi.py
ocpiupdate/py.typed
ocpiupdate/version.py
ocpiupdate/xml.py
ocpiupdate/executables/__main__.py
ocpiupdate/executables/ocpifindsymlink.py
ocpiupdate/executables/ocpiparsemake.py
ocpiupdate/executables/ocpiparsexml.py
ocpiupdate/treesitter/__init__.py
ocpiupdate/treesitter/error.py
ocpiupdate/treesitter/makefile.py
ocpiupdate/treesitter/node.py
ocpiupdate/treesitter/parser.py
ocpiupdate/treesitter/xml.py
ocpiupdate-0.6.4.dist-info/METADATA
ocpiupdate-0.6.4.dist-info/WHEEL
ocpiupdate-0.6.4.dist-info/entry_points.txt
ocpiupdate-0.6.4.dist-info/licenses/LICENSE
ocpiupdate-0.6.4.dist-info/RECORD
